hurry/query/__init__.py
hurry/query/configure.zcml
hurry/query/interfaces.py
hurry/query/query.py
hurry/query/set.py
hurry/query/value.py
hurry/query/tests/__init__.py
hurry/query/tests/test_doctests.py
hurry/query/tests/test_query.py
hurry_query-5.1.dist-info/licenses/LICENSE.txt
hurry_query-5.1.dist-info/METADATA
hurry_query-5.1.dist-info/WHEEL
hurry_query-5.1.dist-info/top_level.txt
hurry_query-5.1.dist-info/RECORD
