Metadata-Version: 2.4
Name: hurry.query
Version: 5.1
Summary: Higher level query system for zope.catalog.
Home-page: https://github.com/zopefoundation/hurry.query
Author: Infrae
Author-email: zope-dev@zope.dev
License: ZPL-2.1
Keywords: zope zope3 catalog index query
Classifier: Development Status :: 5 - Production/Stable
Classifier: Natural Language :: English
Classifier: Operating System :: OS Independent
Classifier: Topic :: Internet :: WWW/HTTP
Classifier: Environment :: Web Environment
Classifier: Intended Audience :: Developers
Classifier: License :: OSI Approved :: Zope Public License
Classifier: Programming Language :: Python
Classifier: Programming Language :: Python :: 3
Classifier: Programming Language :: Python :: 3.10
Classifier: Programming Language :: Python :: 3.11
Classifier: Programming Language :: Python :: 3.12
Classifier: Programming Language :: Python :: 3.13
Classifier: Programming Language :: Python :: 3.14
Classifier: Programming Language :: Python :: Implementation
Classifier: Programming Language :: Python :: Implementation :: CPython
Classifier: Programming Language :: Python :: Implementation :: PyPy
Classifier: Framework :: Zope :: 3
Requires-Python: >=3.10
License-File: LICENSE.txt
Requires-Dist: BTrees
Requires-Dist: setuptools
Requires-Dist: transaction
Requires-Dist: zc.catalog
Requires-Dist: zope.cachedescriptors
Requires-Dist: zope.catalog
Requires-Dist: zope.component
Requires-Dist: zope.index
Requires-Dist: zope.interface
Requires-Dist: zope.intid
Requires-Dist: zope.location
Provides-Extra: test
Requires-Dist: testfixtures; extra == "test"
Requires-Dist: zope.container; extra == "test"
Dynamic: author
Dynamic: author-email
Dynamic: classifier
Dynamic: description
Dynamic: home-page
Dynamic: keywords
Dynamic: license
Dynamic: license-file
Dynamic: provides-extra
Dynamic: requires-dist
Dynamic: requires-python
Dynamic: summary
